amauta_ai/__init__.py
amauta_ai/__main__.py
amauta_ai/ai/__init__.py
amauta_ai/ai/command_base.py
amauta_ai/ai/prompts.py
amauta_ai/ai/provider_selection.py
amauta_ai/ai/providers/__init__.py
amauta_ai/ai/providers/anthropic_provider.py
amauta_ai/ai/providers/base_provider.py
amauta_ai/ai/providers/perplexity_provider.py
amauta_ai/ai/response_validation/__init__.py
amauta_ai/ai/response_validation/integration.py
amauta_ai/ai/response_validation/schemas.py
amauta_ai/ai/response_validation/utils.py
amauta_ai/ai/service.py
amauta_ai/analyzer/__init__.py
amauta_ai/analyzer/commands/__init__.py
amauta_ai/analyzer/commands/architecture.py
amauta_ai/analyzer/complexity.py
amauta_ai/analyzer/framework_detection/__init__.py
amauta_ai/analyzer/framework_detection/base.py
amauta_ai/analyzer/framework_detection/javascript.py
amauta_ai/analyzer/framework_detection/python.py
amauta_ai/analyzer/framework_detection/registry.py
amauta_ai/analyzer/framework_detection/web.py
amauta_ai/analyzer/scanner.py
amauta_ai/analyzer/service.py
amauta_ai/analyzer/visualization.py
amauta_ai/cli/__init__.py
amauta_ai/cli/commands/__init__.py
amauta_ai/cli/commands/config.py
amauta_ai/config/__init__.py
amauta_ai/config/env_manager.py
amauta_ai/config/models.py
amauta_ai/config/override_manager.py
amauta_ai/config/service.py
amauta_ai/exports/__init__.py
amauta_ai/exports/ai.py
amauta_ai/exports/analyzer.py
amauta_ai/exports/config.py
amauta_ai/exports/export_manager.py
amauta_ai/exports/mcp.py
amauta_ai/exports/rules.py
amauta_ai/exports/summarizer.py
amauta_ai/exports/task_manager.py
amauta_ai/imports/__init__.py
amauta_ai/imports/exceptions.py
amauta_ai/imports/lazy_import.py
amauta_ai/main.py
amauta_ai/mcp/.complexity_cache.json
amauta_ai/mcp/__init__.py
amauta_ai/mcp/command.py
amauta_ai/mcp/server.py
amauta_ai/reporter/__init__.py
amauta_ai/reporter/service.py
amauta_ai/rules/__init__.py
amauta_ai/rules/generator.py
amauta_ai/rules/template_manager.py
amauta_ai-1.0.17.dist-info/LICENSE
amauta_ai-1.0.17.dist-info/METADATA
amauta_ai-1.0.17.dist-info/WHEEL
amauta_ai-1.0.17.dist-info/entry_points.txt
amauta_ai-1.0.17.dist-info/RECORD
