Metadata-Version: 2.3
Name: amauta-ai
Version: 1.0.17
Summary: AMAUTA: Autonomous Modular Agent for Unified Task Assistance
License: MIT
Keywords: ai,development,code analysis,task management,cli,cursor,ide,productivity
Author: AI Team
Author-email: ai@amauta.ai
Requires-Python: >=3.10,<4.0
Classifier: Development Status :: 4 - Beta
Classifier: Environment :: Console
Classifier: Intended Audience :: Developers
Classifier: License :: OSI Approved :: MIT License
Classifier: Programming Language :: Python :: 3
Classifier: Programming Language :: Python :: 3.10
Classifier: Programming Language :: Python :: 3.11
Classifier: Programming Language :: Python :: 3.12
Classifier: Programming Language :: Python :: 3.13
Classifier: Programming Language :: Python :: 3.8
Classifier: Programming Language :: Python :: 3.9
Classifier: Topic :: Software Development :: Code Generators
Classifier: Topic :: Software Development :: Libraries :: Python Modules
Classifier: Topic :: Software Development :: Quality Assurance
Classifier: Topic :: Utilities
Provides-Extra: ai
Requires-Dist: aiohttp (>=3.10.11,<4.0.0)
Requires-Dist: anthropic (>=0.49.0) ; extra == "ai"
Requires-Dist: jinja2 (>=3.1.6,<4.0.0)
Requires-Dist: markdown-it-py (>=3.0.0,<4.0.0)
Requires-Dist: pathspec (>=0.12.1,<0.13.0)
Requires-Dist: perplexipy (>=1.2.0) ; extra == "ai"
Requires-Dist: pydantic (>=2.11.2,<3.0.0)
Requires-Dist: pygments (>=2.19.1,<3.0.0)
Requires-Dist: python-dateutil (>=2.9.0,<3.0.0)
Requires-Dist: python-dotenv (>=1.0.1,<2.0.0)
Requires-Dist: pyyaml (>=6.0.1,<7.0.0)
Requires-Dist: requests (>=2.32.3,<3.0.0)
Requires-Dist: rich (>=13.9.4,<14.0.0)
Requires-Dist: shellingham (>=1.5.4,<2.0.0)
Requires-Dist: tomli (>=2.0.1,<3.0.0)
Requires-Dist: tqdm (>=4.66.4,<5.0.0)
Requires-Dist: tree-sitter (>=0.20.2,<0.21.0)
Requires-Dist: typer[all] (>=0.9.0)
Requires-Dist: typing-extensions (>=4.13.0,<5.0.0)
Project-URL: Bug Tracker, https://github.com/luiscmogrovejo/amauta/issues
Project-URL: Changelog, https://github.com/luiscmogrovejo/amauta/blob/main/CHANGELOG.md
Project-URL: Documentation, https://github.com/luiscmogrovejo/amauta
Project-URL: Homepage, https://github.com/luiscmogrovejo/amauta
Project-URL: Repository, https://github.com/luiscmogrovejo/amauta
